[
    {
        "id": 2,
        "nombre": "Oliver",
        "apellidos": "Atom",
        "fecha_nacimiento": "1983-04-10",
        "fecha_incorporacion": "1983-04-10",
        "salario": 35000.0,
        "pais": "España",
        "rol": "Jugador",
        "especialidad": "",
        "posicion": "DELANTERO",
        "dorsal": 10,
        "altura": 1.75,
        "peso": 65.0,
        "goles": 70,
        "partidos_jugados": 150
    },
    {
        "id": 3,
        "nombre": "Benji",
        "apellidos": "Price",
        "fecha_nacimiento": "1983-11-07",
        "fecha_incorporacion": "1983-11-07",
        "salario": 34000.0,
        "pais": "Alemania",
        "rol": "Jugador",
        "especialidad": "",
        "posicion": "PORTERO",
        "dorsal": 1,
        "altura": 1.83,
        "peso": 78.0,
        "goles": 0,
        "partidos_jugados": 200
    },
    {
        "id": 4,
        "nombre": "Freddy",
        "apellidos": "Marshall",
        "fecha_nacimiento": "1965-09-22",
        "fecha_incorporacion": "1965-09-22",
        "salario": 55000.0,
        "pais": "España",
        "rol": "Entrenador",
        "especialidad": "ENTRENADOR_PORTEROS",
        "posicion": "",
        "dorsal": null,
        "altura": null,
        "peso": null,
        "goles": null,
        "partidos_jugados": null
    },
    {
        "id": 5,
        "nombre": "Tom",
        "apellidos": "Baker",
        "fecha_nacimiento": "1984-03-20",
        "fecha_incorporacion": "1984-03-20",
        "salario": 32000.0,
        "pais": "Inglaterra",
        "rol": "Jugador",
        "especialidad": "",
        "posicion": "CENTROCAMPISTA",
        "dorsal": 8,
        "altura": 1.72,
        "peso": 63.0,
        "goles": 30,
        "partidos_jugados": 140
    },
    {
        "id": 6,
        "nombre": "Bruce",
        "apellidos": "Harper",
        "fecha_nacimiento": "1983-08-15",
        "fecha_incorporacion": "1983-08-15",
        "salario": 30000.0,
        "pais": "España",
        "rol": "Jugador",
        "especialidad": "",
        "posicion": "DEFENSA",
        "dorsal": 4,
        "altura": 1.78,
        "peso": 70.0,
        "goles": 5,
        "partidos_jugados": 180
    },
    {
        "id": 7,
        "nombre": "Jefferson",
        "apellidos": "Robles",
        "fecha_nacimiento": "1968-12-12",
        "fecha_incorporacion": "1968-12-12",
        "salario": 58000.0,
        "pais": "México",
        "rol": "Entrenador",
        "especialidad": "ENTRENADOR_ASISTENTE",
        "posicion": "",
        "dorsal": null,
        "altura": null,
        "peso": null,
        "goles": null,
        "partidos_jugados": null
    },
    {
        "id": 8,
        "nombre": "Phillip",
        "apellidos": "Callahan",
        "fecha_nacimiento": "1983-06-06",
        "fecha_incorporacion": "1983-06-06",
        "salario": 31000.0,
        "pais": "Italia",
        "rol": "Jugador",
        "especialidad": "",
        "posicion": "DEFENSA",
        "dorsal": 5,
        "altura": 1.8,
        "peso": 72.0,
        "goles": 10,
        "partidos_jugados": 160
    },
    {
        "id": 9,
        "nombre": "Johnny",
        "apellidos": "Mason",
        "fecha_nacimiento": "1984-01-25",
        "fecha_incorporacion": "1984-01-25",
        "salario": 31000.0,
        "pais": "España",
        "rol": "Jugador",
        "especialidad": "",
        "posicion": "CENTROCAMPISTA",
        "dorsal": 6,
        "altura": 1.74,
        "peso": 68.0,
        "goles": 15,
        "partidos_jugados": 130
    },
    {
        "id": 10,
        "nombre": "Leo",
        "apellidos": "Aragones",
        "fecha_nacimiento": "1970-05-30",
        "fecha_incorporacion": "1970-05-30",
        "salario": 57000.0,
        "pais": "Argentina",
        "rol": "Entrenador",
        "especialidad": "ENTRENADOR_PRINCIPAL",
        "posicion": "",
        "dorsal": null,
        "altura": null,
        "peso": null,
        "goles": null,
        "partidos_jugados": null
    },
    {
        "id": 11,
        "nombre": "Paul",
        "apellidos": "Diamond",
        "fecha_nacimiento": "1983-10-18",
        "fecha_incorporacion": "1983-10-18",
        "salario": 29000.0,
        "pais": "España",
        "rol": "Jugador",
        "especialidad": "",
        "posicion": "DELANTERO",
        "dorsal": 9,
        "altura": 1.76,
        "peso": 67.0,
        "goles": 40,
        "partidos_jugados": 145
    },
    {
        "id": 12,
        "nombre": "Ed",
        "apellidos": "Warner",
        "fecha_nacimiento": "1983-02-02",
        "fecha_incorporacion": "1983-02-02",
        "salario": 32000.0,
        "pais": "España",
        "rol": "Jugador",
        "especialidad": "",
        "posicion": "PORTERO",
        "dorsal": 22,
        "altura": 1.85,
        "peso": 80.0,
        "goles": 0,
        "partidos_jugados": 180
    },
    {
        "id": 13,
        "nombre": "Danny",
        "apellidos": "Mello",
        "fecha_nacimiento": "1984-09-09",
        "fecha_incorporacion": "1984-09-09",
        "salario": 31000.0,
        "pais": "España",
        "rol": "Jugador",
        "especialidad": "",
        "posicion": "DELANTERO",
        "dorsal": 11,
        "altura": 1.77,
        "peso": 69.0,
        "goles": 25,
        "partidos_jugados": 135
    },
    {
        "id": 14,
        "nombre": "Ted",
        "apellidos": "Carter",
        "fecha_nacimiento": "1983-07-07",
        "fecha_incorporacion": "1983-07-07",
        "salario": 30000.0,
        "pais": "España",
        "rol": "Jugador",
        "especialidad": "",
        "posicion": "CENTROCAMPISTA",
        "dorsal": 7,
        "altura": 1.73,
        "peso": 66.0,
        "goles": 20,
        "partidos_jugados": 125
    },
    {
        "id": 15,
        "nombre": "Jack",
        "apellidos": "Morris",
        "fecha_nacimiento": "1984-11-11",
        "fecha_incorporacion": "1984-11-11",
        "salario": 33000.0,
        "pais": "España",
        "rol": "Jugador",
        "especialidad": "",
        "posicion": "DEFENSA",
        "dorsal": 3,
        "altura": 1.79,
        "peso": 71.0,
        "goles": 8,
        "partidos_jugados": 155
    },
    {
        "id": 16,
        "nombre": "Ralph",
        "apellidos": "Peterson",
        "fecha_nacimiento": "1983-05-05",
        "fecha_incorporacion": "1983-05-05",
        "salario": 32000.0,
        "pais": "España",
        "rol": "Jugador",
        "especialidad": "",
        "posicion": "PORTERO",
        "dorsal": 13,
        "altura": 1.84,
        "peso": 79.0,
        "goles": 0,
        "partidos_jugados": 170
    },
    {
        "id": 17,
        "nombre": "Charlie",
        "apellidos": "Custer",
        "fecha_nacimiento": "1984-08-08",
        "fecha_incorporacion": "1984-08-08",
        "salario": 29500.0,
        "pais": "España",
        "rol": "Jugador",
        "especialidad": "",
        "posicion": "DELANTERO",
        "dorsal": 14,
        "altura": 1.78,
        "peso": 68.0,
        "goles": 22,
        "partidos_jugados": 140
    },
    {
        "id": 18,
        "nombre": "David",
        "apellidos": "Evans",
        "fecha_nacimiento": "1983-12-12",
        "fecha_incorporacion": "1983-12-12",
        "salario": 28500.0,
        "pais": "España",
        "rol": "Jugador",
        "especialidad": "",
        "posicion": "CENTROCAMPISTA",
        "dorsal": 15,
        "altura": 1.75,
        "peso": 67.0,
        "goles": 18,
        "partidos_jugados": 115
    },
    {
        "id": 19,
        "nombre": "Patrick",
        "apellidos": "Everett",
        "fecha_nacimiento": "1984-06-06",
        "fecha_incorporacion": "1984-06-06",
        "salario": 32000.0,
        "pais": "España",
        "rol": "Jugador",
        "especialidad": "",
        "posicion": "DEFENSA",
        "dorsal": 2,
        "altura": 1.81,
        "peso": 73.0,
        "goles": 6,
        "partidos_jugados": 150
    },
    {
        "id": 20,
        "nombre": "Richard",
        "apellidos": "Textex",
        "fecha_nacimiento": "1983-03-03",
        "fecha_incorporacion": "1983-03-03",
        "salario": 27500.0,
        "pais": "España",
        "rol": "Jugador",
        "especialidad": "",
        "posicion": "PORTERO",
        "dorsal": 16,
        "altura": 1.86,
        "peso": 82.0,
        "goles": 0,
        "partidos_jugados": 1601
    },
    {
        "id": 21,
        "nombre": "Carlos",
        "apellidos": "Santana",
        "fecha_nacimiento": "1985-01-15",
        "fecha_incorporacion": "1985-01-15",
        "salario": 33000.0,
        "pais": "Brasil",
        "rol": "Jugador",
        "especialidad": "",
        "posicion": "DELANTERO",
        "dorsal": 9,
        "altura": 1.82,
        "peso": 74.0,
        "goles": 50,
        "partidos_jugados": 140
    },
    {
        "id": 22,
        "nombre": "Miguel",
        "apellidos": "Rodriguez",
        "fecha_nacimiento": "1982-11-30",
        "fecha_incorporacion": "1982-11-30",
        "salario": 34000.0,
        "pais": "España",
        "rol": "Jugador",
        "especialidad": "",
        "posicion": "CENTROCAMPISTA",
        "dorsal": 8,
        "altura": 1.76,
        "peso": 70.0,
        "goles": 25,
        "partidos_jugados": 150
    },
    {
        "id": 23,
        "nombre": "Luca",
        "apellidos": "Bianchi",
        "fecha_nacimiento": "1987-06-20",
        "fecha_incorporacion": "1987-06-20",
        "salario": 32000.0,
        "pais": "Italia",
        "rol": "Jugador",
        "especialidad": "",
        "posicion": "DEFENSA",
        "dorsal": 4,
        "altura": 1.85,
        "peso": 78.0,
        "goles": 5,
        "partidos_jugados": 160
    },
    {
        "id": 24,
        "nombre": "Hans",
        "apellidos": "Keller",
        "fecha_nacimiento": "1980-04-18",
        "fecha_incorporacion": "1980-04-18",
        "salario": 36000.0,
        "pais": "Alemania",
        "rol": "Entrenador",
        "especialidad": "ENTRENADOR_ASISTENTE",
        "posicion": "",
        "dorsal": null,
        "altura": null,
        "peso": null,
        "goles": null,
        "partidos_jugados": null
    },
    {
        "id": 25,
        "nombre": "Juan",
        "apellidos": "Perez",
        "fecha_nacimiento": "1986-09-25",
        "fecha_incorporacion": "1986-09-25",
        "salario": 29000.0,
        "pais": "México",
        "rol": "Jugador",
        "especialidad": "",
        "posicion": "PORTERO",
        "dorsal": 1,
        "altura": 1.9,
        "peso": 85.0,
        "goles": 0,
        "partidos_jugados": 180
    },
    {
        "id": 26,
        "nombre": "Nicolas",
        "apellidos": "Gomez",
        "fecha_nacimiento": "1984-03-05",
        "fecha_incorporacion": "1984-03-05",
        "salario": 31000.0,
        "pais": "Argentina",
        "rol": "Jugador",
        "especialidad": "",
        "posicion": "DELANTERO",
        "dorsal": 11,
        "altura": 1.8,
        "peso": 72.0,
        "goles": 45,
        "partidos_jugados": 135
    },
    {
        "id": 27,
        "nombre": "Takeshi",
        "apellidos": "Yamamoto",
        "fecha_nacimiento": "1983-07-30",
        "fecha_incorporacion": "1983-07-30",
        "salario": 28000.0,
        "pais": "Japón",
        "rol": "Jugador",
        "especialidad": "",
        "posicion": "CENTROCAMPISTA",
        "dorsal": 7,
        "altura": 1.74,
        "peso": 68.0,
        "goles": 18,
        "partidos_jugados": 130
    },
    {
        "id": 28,
        "nombre": "Samuel",
        "apellidos": "Johnson",
        "fecha_nacimiento": "1981-11-11",
        "fecha_incorporacion": "1981-11-11",
        "salario": 37000.0,
        "pais": "Estados Unidos",
        "rol": "Entrenador",
        "especialidad": "ENTRENADOR_ASISTENTE",
        "posicion": "",
        "dorsal": null,
        "altura": null,
        "peso": null,
        "goles": null,
        "partidos_jugados": null
    },
    {
        "id": 29,
        "nombre": "Pierre",
        "apellidos": "Dupont",
        "fecha_nacimiento": "1985-02-10",
        "fecha_incorporacion": "1985-02-10",
        "salario": 30000.0,
        "pais": "Francia",
        "rol": "Jugador",
        "especialidad": "",
        "posicion": "DEFENSA",
        "dorsal": 5,
        "altura": 1.83,
        "peso": 75.0,
        "goles": 7,
        "partidos_jugados": 145
    },
    {
        "id": 30,
        "nombre": "Igor",
        "apellidos": "Petrov",
        "fecha_nacimiento": "1982-04-04",
        "fecha_incorporacion": "1982-04-04",
        "salario": 35000.0,
        "pais": "Rusia",
        "rol": "Jugador",
        "especialidad": "",
        "posicion": "DELANTERO",
        "dorsal": 10,
        "altura": 1.88,
        "peso": 80.0,
        "goles": 55,
        "partidos_jugados": 150
    },
    {
        "id": 31,
        "nombre": "Luisa",
        "apellidos": "Martinez",
        "fecha_nacimiento": "1987-01-21",
        "fecha_incorporacion": "1987-01-21",
        "salario": 31000.0,
        "pais": "España",
        "rol": "Jugador",
        "especialidad": "",
        "posicion": "CENTROCAMPISTA",
        "dorsal": 6,
        "altura": 1.7,
        "peso": 65.0,
        "goles": 20,
        "partidos_jugados": 125
    },
    {
        "id": 32,
        "nombre": "Anita",
        "apellidos": "Lopez",
        "fecha_nacimiento": "1986-05-12",
        "fecha_incorporacion": "1986-05-12",
        "salario": 29000.0,
        "pais": "Chile",
        "rol": "Jugador",
        "especialidad": "",
        "posicion": "DEFENSA",
        "dorsal": 3,
        "altura": 1.75,
        "peso": 68.0,
        "goles": 10,
        "partidos_jugados": 140
    },
    {
        "id": 33,
        "nombre": "Erik",
        "apellidos": "Svensson",
        "fecha_nacimiento": "1983-09-09",
        "fecha_incorporacion": "1983-09-09",
        "salario": 34000.0,
        "pais": "Suecia",
        "rol": "Jugador",
        "especialidad": "",
        "posicion": "PORTERO",
        "dorsal": 12,
        "altura": 1.92,
        "peso": 82.0,
        "goles": 0,
        "partidos_jugados": 170
    },
    {
        "id": 34,
        "nombre": "Alicia",
        "apellidos": "Fernandez",
        "fecha_nacimiento": "1984-07-17",
        "fecha_incorporacion": "1984-07-17",
        "salario": 33000.0,
        "pais": "España",
        "rol": "Jugador",
        "especialidad": "",
        "posicion": "DELANTERO",
        "dorsal": 13,
        "altura": 1.77,
        "peso": 70.0,
        "goles": 40,
        "partidos_jugados": 130
    },
    {
        "id": 35,
        "nombre": "Diego",
        "apellidos": "Cruz",
        "fecha_nacimiento": "1982-03-03",
        "fecha_incorporacion": "1982-03-03",
        "salario": 32000.0,
        "pais": "Uruguay",
        "rol": "Jugador",
        "especialidad": "",
        "posicion": "CENTROCAMPISTA",
        "dorsal": 14,
        "altura": 1.78,
        "peso": 72.0,
        "goles": 22,
        "partidos_jugados": 150
    },
    {
        "id": 36,
        "nombre": "Sofia",
        "apellidos": "Gonzalez",
        "fecha_nacimiento": "1985-10-10",
        "fecha_incorporacion": "1985-10-10",
        "salario": 31000.0,
        "pais": "Argentina",
        "rol": "Jugador",
        "especialidad": "",
        "posicion": "DEFENSA",
        "dorsal": 2,
        "altura": 1.8,
        "peso": 74.0,
        "goles": 8,
        "partidos_jugados": 135
    },
    {
        "id": 37,
        "nombre": "Hiroshi",
        "apellidos": "Tanaka",
        "fecha_nacimiento": "1984-06-06",
        "fecha_incorporacion": "1984-06-06",
        "salario": 30000.0,
        "pais": "Japón",
        "rol": "Jugador",
        "especialidad": "",
        "posicion": "PORTERO",
        "dorsal": 23,
        "altura": 1.84,
        "peso": 79.0,
        "goles": 0,
        "partidos_jugados": 160
    },
    {
        "id": 38,
        "nombre": "Marco",
        "apellidos": "Rossi",
        "fecha_nacimiento": "1983-12-12",
        "fecha_incorporacion": "1983-12-12",
        "salario": 34000.0,
        "pais": "Italia",
        "rol": "Jugador",
        "especialidad": "",
        "posicion": "DELANTERO",
        "dorsal": 15,
        "altura": 1.81,
        "peso": 76.0,
        "goles": 48,
        "partidos_jugados": 145
    },
    {
        "id": 39,
        "nombre": "Elena",
        "apellidos": "Garcia",
        "fecha_nacimiento": "1986-08-08",
        "fecha_incorporacion": "1986-08-08",
        "salario": 32000.0,
        "pais": "España",
        "rol": "Jugador",
        "especialidad": "",
        "posicion": "CENTROCAMPISTA",
        "dorsal": 16,
        "altura": 1.72,
        "peso": 67.0,
        "goles": 19,
        "partidos_jugados": 120
    },
    {
        "id": 40,
        "nombre": "Pedro",
        "apellidos": "Silva",
        "fecha_nacimiento": "1984-11-11",
        "fecha_incorporacion": "1984-11-11",
        "salario": 31000.0,
        "pais": "Portugal",
        "rol": "Jugador",
        "especialidad": "",
        "posicion": "DEFENSA",
        "dorsal": 17,
        "altura": 1.86,
        "peso": 77.0,
        "goles": 9,
        "partidos_jugados": 155
    }
]